[
  {
    "nomor": 78,
    "nama": "An-Nabaʼ",
    "ayat": [
      {
        "nomor": 1,
        "arab": "عَمَّ يَتَسَاءَلُونَ",
        "latin": "'Amma yatasa'alūn",
        "arti": "Tentang apakah mereka saling bertanya-tanya?"
      },
      {
        "nomor": 2,
        "arab": "عَنِ النَّبَإِ الْعَظِيمِ",
        "latin": "'Ani n-naba'il-'azīm",
        "arti": "Tentang berita yang besar,"
      }
    ]
  },
  {
    "nomor": 79,
    "nama": "An-Nazi'at",
    "ayat": [
      {
        "nomor": 1,
        "arab": "وَالنَّازِعَاتِ غَرْقًا",
        "latin": "Wan-nāzi'āti gharqā",
        "arti": "Demi (malaikat) yang mencabut (nyawa) dengan keras,"
      }
    ]
  }
]
